CHANGELOG.md
LICENSE.txt
MANIFEST.in
README.md
setup.py
jsond/__init__.py
jsond.egg-info/PKG-INFO
jsond.egg-info/SOURCES.txt
jsond.egg-info/dependency_links.txt
jsond.egg-info/requires.txt
jsond.egg-info/top_level.txt