Metadata-Version: 2.1
Name: jsond
Version: 1.4.0
Summary: JSON (with dates)
Home-page: https://github.com/EDITD/jsond
Author: EDITED devs
Author-email: dev@edited.com
License: MIT
Platform: UNKNOWN
Classifier: License :: OSI Approved :: MIT License
Classifier: Development Status :: 5 - Production/Stable
Classifier: Operating System :: OS Independent
Classifier: Programming Language :: Python :: 2
Classifier: Programming Language :: Python :: 3
Classifier: Programming Language :: Python :: 3.4
Classifier: Programming Language :: Python :: 3.5
Classifier: Programming Language :: Python :: 3.6
Classifier: Programming Language :: Python :: 3.7
Classifier: Programming Language :: Python :: 3.8
Classifier: Topic :: Software Development :: Libraries :: Python Modules
Requires-Python: >=2.7, !=3.0.*, !=3.1.*, !=3.2.*, !=3.3.*
Provides-Extra: dev
